{
    "prepare_queue": {
        "installed": [],
        "uninstalled": []
    },
    "config_munge": {
        "files": {
            "res/xml/config.xml": {
                "parents": {
                    "/*": [
                        {
                            "xml": "<feature name=\"Keyboard\"><param name=\"android-package\" value=\"com.ionic.keyboard.IonicKeyboard\" /><param name=\"onload\" value=\"true\" /></feature>",
                            "count": 1
                        },
                        {
                            "xml": "<feature name=\"EmailComposer\"><param name=\"android-package\" value=\"com.jcjee.plugins.EmailComposer\" /></feature>",
                            "count": 1
                        },
                        {
                            "xml": "<feature name=\"EmailComposer\"><param name=\"android-package\" value=\"de.appplant.cordova.emailcomposer.EmailComposer\" /></feature>",
                            "count": 1
                        },
                        {
                            "xml": "<feature name=\"Device\"><param name=\"android-package\" value=\"org.apache.cordova.device.Device\" /></feature>",
                            "count": 1
                        }
                    ]
                }
            },
            "AndroidManifest.xml": {
                "parents": {
                    "application": [
                        {
                            "xml": "<provider android:authorities=\"com.ionicframework.proposal801592.plugins.emailcomposer.provider\" android:name=\"com.jcjee.plugins.EmailAttachmentProvider\" />",
                            "count": 1
                        }
                    ]
                }
            }
        }
    },
    "installed_plugins": {
        "com.ionic.keyboard": {
            "PACKAGE_NAME": "com.ionicframework.proposal801592"
        },
        "com.jcjee.plugins.emailcomposer": {
            "PACKAGE_NAME": "com.ionicframework.proposal801592"
        },
        "de.appplant.cordova.plugin.email-composer": {
            "PACKAGE_NAME": "com.ionicframework.proposal801592"
        },
        "org.apache.cordova.console": {
            "PACKAGE_NAME": "com.ionicframework.proposal801592"
        },
        "org.apache.cordova.device": {
            "PACKAGE_NAME": "com.ionicframework.proposal801592"
        }
    },
    "dependent_plugins": {}
}